README.md
setup.py
xpkg/__init__.py
xpkg/debug.py
xpkg/terminal.py
xpkg.egg-info/PKG-INFO
xpkg.egg-info/SOURCES.txt
xpkg.egg-info/dependency_links.txt
xpkg.egg-info/top_level.txt